{
  "generator-jhipster": {
    "applicationType": "monolith",
    "authenticationType": "oauth2",
    "baseName": "hbTemplate",
    "blueprints": [],
    "buildTool": "maven",
    "cacheProvider": "redis",
    "clientFramework": "angularX",
    "clientPackageManager": "npm",
    "clientTheme": "none",
    "clientThemeVariant": "",
    "creationTimestamp": 1671258931790,
    "databaseType": "sql",
    "devDatabaseType": "h2Disk",
    "devServerPort": 4200,
    "dtoSuffix": "DTO",
    "enableGradleEnterprise": false,
    "enableHibernateCache": true,
    "enableSwaggerCodegen": "true",
    "enableTranslation": true,
    "entitySuffix": "",
    "gitCompany": "",
    "jhiPrefix": "jhi",
    "jhipsterVersion": "7.9.3",
    "languages": ["en", "ar-ly"],
    "messageBroker": "kafka",
    "nativeLanguage": "en",
    "otherModules": [],
    "packageFolder": "xyz/hb",
    "packageName": "xyz.hb",
    "pages": [],
    "prodDatabaseType": "postgresql",
    "reactive": false,
    "searchEngine": "elasticsearch",
    "serverPort": 8080,
    "serviceDiscoveryType": false,
    "skipCheckLengthOfIdentifier": false,
    "skipClient": false,
    "skipFakeData": false,
    "skipUserManagement": true,
    "testFrameworks": ["protractor"],
    "useSass": true,
    "websocket": "spring-websocket",
    "withAdminUi": true
  },
  "git-provider": "GitHub",
  "git-company": "hbadri1",
  "repository-name": "hb-template"
}
